{"name":"Quadcopter","tagline":"Driver for controlled quadcopter flight","body":"Quadcopter\r\n==========\r\n\r\nAuthors: Brandon Riches, Andrew Coulthard, Branden Yue  <br />\r\nDate   : May 2013 <br />\r\nVersion: 0.7 <br />\r\n\r\nDescription\r\n-----------\r\n\r\nIts quadcopter flight software!  \r\n<br /><br />\r\n\r\nMCU: Osepp Mega 2560 R3   \r\n(Soon switching to the chipKIT uC32 with the PIC32)  \r\n\r\n\r\n<br />\r\nCurrent sensors lineup:\r\n - LSM303 Accelerometer / Magnetometer \r\n - MPU3050 Gyro\r\n - Adafruit ultimate GPS module\r\n - RTC Module (DS1307)\r\n - Maxbotix USRF (LV-EZ1)\r\n - BMP085 Barometeric Pressure/Temperature/Altitude\r\n \r\n\r\nUnder development currently:\r\n----------------------------\r\n\r\n <br />\r\n  - Digital filtering of accel and gyro data <br />\r\n\r\n  - GPS integration and datalogging <br />\r\n      - See [QCopterMain.ino](https://github.com/briches/Quadcopter/blob/master/QCopterMain/QCopterMain.ino) for info. <br />\r\n\r\n\r\nFeatures and long term goals:\r\n----------------------------\r\n   <br />\r\n  - Fully autonomous takeoff and landing. Has the option to be controlled via radio comms. <br />\r\n\r\n  - 9DOF sensor module (IMU) with GPS and localization  <br />\r\n  \r\n  - Open source =]\r\n   <br />\r\n   <br />\r\n\r\n\r\n","google":"","note":"Don't delete this file! It's used internally to help with page regeneration."}